vumi_wikipedia/__init__.py
vumi_wikipedia/text_manglers.py
vumi_wikipedia/wikipedia.py
vumi_wikipedia/wikipedia_api.py
vumi_wikipedia/tests/__init__.py
vumi_wikipedia/tests/test_text_manglers.py
vumi_wikipedia/tests/test_wikipedia.py
vumi_wikipedia/tests/test_wikipedia_api.py
vumi_wikipedia/tests/uss_responses.json
vumi_wikipedia/tests/wikipedia_responses.json
vumi_wikipedia-0.2.1.dist-info/DESCRIPTION.rst
vumi_wikipedia-0.2.1.dist-info/METADATA
vumi_wikipedia-0.2.1.dist-info/metadata.json
vumi_wikipedia-0.2.1.dist-info/RECORD
vumi_wikipedia-0.2.1.dist-info/top_level.txt
vumi_wikipedia-0.2.1.dist-info/WHEEL
