Metadata-Version: 2.0
Name: vumi-wikipedia
Version: 0.2.1
Summary: Vumi Wikipedia App
Home-page: http://github.com/praekelt/vumi-wikipedia
Author: Praekelt Foundation
Author-email: dev@praekelt.com
License: BSD
Platform: UNKNOWN
Classifier: Development Status :: 4 - Beta
Classifier: Intended Audience :: Developers
Classifier: License :: OSI Approved :: BSD License
Classifier: Operating System :: POSIX
Classifier: Programming Language :: Python :: 2.6
Classifier: Programming Language :: Python :: 2.7
Classifier: Topic :: Software Development :: Libraries :: Python Modules
Classifier: Topic :: System :: Networking
Requires-Dist: vumi (>=0.5)
Requires-Dist: unidecode
